LICENSE
MANIFEST.in
README.md
setup.cfg
setup.py
versioneer.py
./.gitattributes
./CODE_OF_CONDUCT.md
./CONTRIBUTING.md
./LICENSE
./MANIFEST.in
./README.md
./setup.cfg
./setup.py
./versioneer.py
./colorstylecycler/__init__.py
./colorstylecycler/_version.py
./colorstylecycler/cycler.py
./colorstylecycler.egg-info/PKG-INFO
./colorstylecycler.egg-info/SOURCES.txt
./colorstylecycler.egg-info/dependency_links.txt
./colorstylecycler.egg-info/requires.txt
./colorstylecycler.egg-info/top_level.txt
colorstylecycler/__init__.py
colorstylecycler/_version.py
colorstylecycler/cycler.py
colorstylecycler.egg-info/PKG-INFO
colorstylecycler.egg-info/SOURCES.txt
colorstylecycler.egg-info/dependency_links.txt
colorstylecycler.egg-info/requires.txt
colorstylecycler.egg-info/top_level.txt