Metadata-Version: 2.1
Name: colorstylecycler
Version: 0.1.22
Summary: Can cycle through combination of colors and line or marker styles
Home-page: https://github.com/Advestis/colorstylecycler
Author: Advestis
Author-email: pythondev@advestis.com
License: GPLv3
Project-URL: Bug Tracker, https://github.com/Advestis/colorstylecycler/issues
Project-URL: Documentation, https://advestis.github.io/colorstylecycler
Project-URL: Source Code, https://github.com/Advestis/colorstylecycler/
Platform: UNKNOWN
Classifier: Development Status :: 5 - Production/Stable
Classifier: License :: OSI Approved :: GNU General Public License v3 (GPLv3)
Classifier: Operating System :: Unix
Classifier: Programming Language :: Python :: 3.7
Classifier: Programming Language :: Python :: 3.8
Classifier: Programming Language :: Python :: 3.9
Requires-Python: >=3.7
License-File: LICENSE
